odoo/addons/base_rest_base_structure/README.rst
odoo/addons/base_rest_base_structure/__init__.py
odoo/addons/base_rest_base_structure/__manifest__.py
odoo/addons/base_rest_base_structure/controllers/__init__.py
odoo/addons/base_rest_base_structure/controllers/main_controllers.py
odoo/addons/base_rest_base_structure/models/api_services_utils.py
odoo/addons/base_rest_base_structure/services/__init__.py
odoo/addons/base_rest_base_structure/services/abstract_services.py
odoo14_addon_base_rest_base_structure-14.0.0.0.1.dist-info/METADATA
odoo14_addon_base_rest_base_structure-14.0.0.0.1.dist-info/WHEEL
odoo14_addon_base_rest_base_structure-14.0.0.0.1.dist-info/top_level.txt
odoo14_addon_base_rest_base_structure-14.0.0.0.1.dist-info/RECORD
