Metadata-Version: 2.1
Name: odoo14-addon-base-rest-base-structure
Version: 14.0.0.0.1
Summary: Provide base controllers and services for simplifiying custom API implementation.
Home-page: https://gitlab.com/coopdevs/odoo-addons
Author: Coopdevs Treball SCCL
License: AGPL-3
Platform: UNKNOWN
Classifier: Programming Language :: Python
Classifier: Framework :: Odoo
Classifier: Framework :: Odoo :: 14.0
Classifier: License :: OSI Approved :: GNU Affero General Public License v3
Requires-Python: >=3.6
Requires-Dist: odoo14-addon-auth-api-key
Requires-Dist: odoo14-addon-base-rest
Requires-Dist: odoo (<14.1dev,>=14.0a)
